<?xml version="1.0" encoding="UTF-8"?>
<databaseChangeLog xmlns="http://www.liquibase.org/xml/ns/dbchangelog"
	xmlns:xsi="http://www.w3.org/2001/XMLSchema-instance" xmlns:ext="http://www.liquibase.org/xml/ns/dbchangelog-ext"
	xsi:schemaLocation="http://www.liquibase.org/xml/ns/dbchangelog
	dbchangelog-3.4.xsd
	http://www.liquibase.org/xml/ns/dbchangelog-ext
	http://www.liquibase.org/xml/ns/dbchangelog/dbchangelog-ext.xsd">

	<changeSet id="010" author="laleska.piaunios">
		<createTable tableName="SCR_INGREDIENTE">
			<column name="ID" type="BIGINT" />
			<column name="DESCRICAO" type="VARCHAR(255)" />
		</createTable>
	</changeSet>

	<changeSet id="020" author="laleska.santos">
		<createTable tableName="SCR_PRODUTO">
			<column name="ID" type="BIGINT" />
			<column name="DESCRICAO" type="VARCHAR(255)" />
			<column name="STATUS" type="VARCHAR(255)" />
			<column name="PRECO" type="DOUBLE" />
		</createTable>
	</changeSet>

	<changeSet id="030" author="laleska.santos">
		<createTable tableName="SCR_ITEM_INGREDIENTE">
			<column name="ID" type="BIGINT" />
			<column name="PROD_ID" type="BIGINT" />
			<column name="INGRED_ID" type="BIGINT" />
			<column name="QUANTIDADE" type="INTEGER" />
		</createTable>
	</changeSet>

	<changeSet id="040" author="laleska.santos">
		<createTable tableName="SCR_ITEM_PROD">
			<column name="PROD_ID" type="BIGINT" />
			<column name="ID_PRODUTO" type="BIGINT" />
			<column name="ID_PEDIDO" type="BIGINT" />
			<column name="PRECO" type="DOUBLE" />
		</createTable>
	</changeSet>

	<changeSet id="050" author="laleska.santos">
		<addPrimaryKey columnNames="ID" tableName="SCR_INGREDIENTE" />
		<addPrimaryKey columnNames="ID" tableName="SCR_PRODUTO" />
		<addPrimaryKey columnNames="PROD_ID" tableName="SCR_ITEM_PROD" />
	</changeSet>


	<changeSet id="060" author="juliano.cesar">
		<createTable tableName="SCR_PEDIDO">
			<column name="ID" type="BIGINT" />
			<column name="STATUS" type="VARCHAR(255)" />
			<column name="DATA_ABERTURA" type="BIGINT" />
			<column name="VALOR_TOTAL" type="DOUBLE" />
			<column name="ID_COMANDA" type="BIGINT" />
			<column name="ID_GARCOM" type="BIGINT" />
		</createTable>
	</changeSet>

	<changeSet id="070" author="juliano.cesar">
		<createTable tableName="SCR_LISTA_PEDIDOS">
			<column name="ID" type="BIGINT" />
			<column name="ID_PEDIDO" type="BIGINT" />
			<column name="STATUS" type="VARCHAR(255)" />
		</createTable>
	</changeSet>

	<changeSet id="080" author="juliano.cesar">
		<createTable tableName="SCR_COMANDA">
			<column name="ID" type="BIGINT" />
			<column name="VALOR_TOTAL" type="DOUBLE" />
			<column name="DATA_ABERTURA" type="BIGINT" />
			<column name="DATA_FECHAMENTO" type="BIGINT" />
		</createTable>
	</changeSet>

	<changeSet id="090" author="juliano.cesar">
		<createTable tableName="SCR_GARCOM">
			<column name="ID" type="BIGINT" />
			<column name="NOME" type="VARCHAR(50)" />
			<column name="REGISTRO" type="VARCHAR(10)" />
			<column name="SEXO" type="VARCHAR(10)" />
			<column name="IDADE" type="NUMBER" />
		</createTable>
	</changeSet>

	<changeSet author="laleska.santos" id="100"
		dbms="oracle, hsqldb, postgresql">
		<createSequence incrementBy="1" sequenceName="SEQ_SCR_INGREDIENTE"
			startValue="1" />

		<createSequence incrementBy="1" sequenceName="SEQ_SCR_PRODUTO"
			startValue="1" />

		<createSequence incrementBy="1" sequenceName="SEQ_SCR_ITEM_INGREDIENTE"
			startValue="1" />

		<createSequence incrementBy="1" sequenceName="SEQ_SCR_ITEM_PROD"
			startValue="1" />
	</changeSet>

	<changeSet author="laleska.santos" id="110" dbms="mysql">
		<addAutoIncrement tableName="SCR_INGREDIENTE"
			columnName="ID" columnDataType="bigint" />
	</changeSet>

	<changeSet author="laleska.santos" id="120" dbms="mysql">
		<addAutoIncrement tableName="SCR_PRODUTO" columnName="ID"
			columnDataType="bigint" />
	</changeSet>

	<changeSet author="laleska.santos" id="130" dbms="mysql">
		<addAutoIncrement tableName="SCR_ITEM_INGREDIENTE"
			columnName="ID" columnDataType="bigint" />
	</changeSet>

	<changeSet author="laleska.santos" id="140" dbms="mysql">
		<addAutoIncrement tableName="SCR_ITEM_INGREDIENTE"
			columnName="ID" columnDataType="bigint" />
	</changeSet>
	
	<changeSet id="150" author="juliano.cesar">
		<addPrimaryKey columnNames="ID" tableName="SCR_PEDIDO" />
		<addPrimaryKey columnNames="ID" tableName="SCR_LISTA_PEDIDOS" />
		<addPrimaryKey columnNames="ID" tableName="SCR_COMANDA" />
		<addPrimaryKey columnNames="ID" tableName="SCR_GARCOM" />
	</changeSet>

	<changeSet author="juliano.rosa" id="160"
		dbms="oracle, hsqldb, postgresql">
		<createSequence incrementBy="1" sequenceName="SEQ_SCR_PEDIDO"
			startValue="1" />

		<createSequence incrementBy="1" sequenceName="SEQ_SCR_LISTA_PEDIDOS"
			startValue="1" />

		<createSequence incrementBy="1" sequenceName="SEQ_SCR_COMANDA"
			startValue="1" />

		<createSequence incrementBy="1" sequenceName="SEQ_SCR_GARCOM"
			startValue="1" />
	</changeSet>

	<changeSet author="juliano.cesar" id="170" dbms="mysql">
		<addAutoIncrement tableName="SCR_PEDIDO" columnName="ID"
			columnDataType="bigint" />
	</changeSet>

	<changeSet author="juliano.cesar" id="180" dbms="mysql">
		<addAutoIncrement tableName="SCR_LISTA_PEDIDOS"
			columnName="ID" columnDataType="bigint" />
	</changeSet>

	<changeSet author="juliano.cesar" id="190" dbms="mysql">
		<addAutoIncrement tableName="SCR_COMANDA" columnName="ID"
			columnDataType="bigint" />
	</changeSet>

	<changeSet author="juliano.cesar" id="200" dbms="mysql">
		<addAutoIncrement tableName="SCR_GARCOM" columnName="ID"
			columnDataType="bigint" />
	</changeSet>

	<changeSet id="210" author="laleska.santos">
		<addForeignKeyConstraint constraintName="FK_ITEM_PROD_PRODUTO"
			referencedTableName="SCR_PRODUTO" referencedColumnNames="ID"
			baseTableName="SCR_ITEM_PROD" baseColumnNames="ID_PRODUTO" />
	<!-- PAU AQUI -->
		<addForeignKeyConstraint constraintName="FK_ITEM_PROD_PEDIDO"
			referencedTableName="SCR_PEDIDO" referencedColumnNames="ID"
			baseTableName="SCR_ITEM_PROD" baseColumnNames="ID_PEDIDO" />
	</changeSet>

	<changeSet id="220" author="laleska.santos">
		<addForeignKeyConstraint constraintName="FK_ITEM_INGREDIENTE_PRODUTO"
			referencedTableName="SCR_PRODUTO" referencedColumnNames="ID"
			baseTableName="SCR_ITEM_INGREDIENTE" baseColumnNames="PROD_ID" />

		<addForeignKeyConstraint constraintName="FK_ITEM_INGREDIENTE_INGREDIENTE"
			referencedTableName="SCR_INGREDIENTE" referencedColumnNames="ID"
			baseTableName="SCR_ITEM_INGREDIENTE" baseColumnNames="INGRED_ID" />
	</changeSet>

	<changeSet id="048" author="juliano.cesar">
		<addForeignKeyConstraint constraintName="FK_PEDIDO_COMANDA"
			referencedTableName="SCR_COMANDA" referencedColumnNames="ID"
			baseTableName="SCR_PEDIDO" baseColumnNames="ID_COMANDA" />
	</changeSet>

	<changeSet id="230" author="juliano.cesar">
		<addForeignKeyConstraint constraintName="FK_PEDIDO_GARCOM"
			referencedTableName="SCR_GARCOM" referencedColumnNames="ID"
			baseTableName="SCR_PEDIDO" baseColumnNames="ID_GARCOM" />
	</changeSet>

	<changeSet id="240" author="juliano.cesar">
		<addForeignKeyConstraint constraintName="FK_LISTA_PEDIDOS_PEDIDO"
			referencedTableName="SCR_PEDIDO" referencedColumnNames="ID"
			baseTableName="SCR_LISTA_PEDIDOS" baseColumnNames="ID_PEDIDO" />
	</changeSet>

</databaseChangeLog>